sol_view/__init__.py
sol_view/fits.py
sol_view/main.py
sol_view/main.ui
sol_view/plot_actions.py
sol_view/plot_hdf5.py
sol_view/plot_hdf5.ui
sol_view/qdialog.py
sol_view/icons/__init__.py
sol_view/icons/cnpem.png
sol_view/icons/lnls-sirius.png
sol_view/scripts/__init__.py
sol_view/scripts/run.py
sol_view-1.0.2.dist-info/METADATA
sol_view-1.0.2.dist-info/WHEEL
sol_view-1.0.2.dist-info/entry_points.txt
sol_view-1.0.2.dist-info/top_level.txt
sol_view-1.0.2.dist-info/RECORD
